IslandPy/RenderObject.py
IslandPy/RenderWindow.py
IslandPy/Scene.py
IslandPy/__init__.py
IslandPy/Render/ARenderObject.py
IslandPy/Render/TestRender.py
IslandPy/Render/__init__.py
IslandPy/Render/UI/Button.py
IslandPy/Render/UI/Indents.py
IslandPy/Render/UI/TextLabel.py
IslandPy/Render/UI/__init__.py
IslandPy/Scenes/AScene.py
IslandPy/Scenes/TestScene.py
IslandPy/Scenes/__init__.py
IslandPy-0.0.0.dev16.dist-info/LICENSE
IslandPy-0.0.0.dev16.dist-info/METADATA
IslandPy-0.0.0.dev16.dist-info/WHEEL
IslandPy-0.0.0.dev16.dist-info/top_level.txt
IslandPy-0.0.0.dev16.dist-info/RECORD
